rcvformats/__init__.py
rcvformats/bin/__init__.py
rcvformats/bin/cli.py
rcvformats/common/__init__.py
rcvformats/common/electionbuddyparser.py
rcvformats/common/utils.py
rcvformats/conversions/__init__.py
rcvformats/conversions/automatic.py
rcvformats/conversions/base.py
rcvformats/conversions/dominion_multi_converter.py
rcvformats/conversions/dominion_txt.py
rcvformats/conversions/dominion_xlsx.py
rcvformats/conversions/electionbuddy.py
rcvformats/conversions/opavote.py
rcvformats/conversions/ut_without_transfers.py
rcvformats/jsonschemas/opavote.schema.json
rcvformats/jsonschemas/opavote_v1_1.schema.json
rcvformats/jsonschemas/universaltabulator.schema.json
rcvformats/schemas/__init__.py
rcvformats/schemas/base.py
rcvformats/schemas/electionbuddy.py
rcvformats/schemas/opavote.py
rcvformats/schemas/universaltabulator.py
rcvformats/test/__init__.py
rcvformats/test/test_conversions.py
rcvformats/test/test_safety.py
rcvformats/test/test_schema.py
rcvformats-0.0.46.dist-info/LICENSE.txt
rcvformats-0.0.46.dist-info/METADATA
rcvformats-0.0.46.dist-info/WHEEL
rcvformats-0.0.46.dist-info/entry_points.txt
rcvformats-0.0.46.dist-info/top_level.txt
rcvformats-0.0.46.dist-info/RECORD
