Metadata-Version: 2.1
Name: rcvformats
Version: 0.0.46
Summary: Schema validations, migrations, and conversions to standardize the Ranked Choice Voting ecosystem
Home-page: https://github.com/artoonie/rcvformats
Author: Armin Samii
Author-email: armin.samii@gmail.com
Requires-Python: >=3
License-File: LICENSE.txt
Requires-Dist: jsonschema
Requires-Dist: openpyxl
Requires-Dist: defusedxml
